model_mommy/__init__.py
model_mommy/exceptions.py
model_mommy/generators.py
model_mommy/gis.py
model_mommy/mock-img.jpeg
model_mommy/mock_file.txt
model_mommy/mommy.py
model_mommy/random_gen.py
model_mommy/recipe.py
model_mommy/timezone.py
model_mommy/utils.py
model_mommy-1.6.0.dist-info/DESCRIPTION.rst
model_mommy-1.6.0.dist-info/METADATA
model_mommy-1.6.0.dist-info/RECORD
model_mommy-1.6.0.dist-info/WHEEL
model_mommy-1.6.0.dist-info/metadata.json
model_mommy-1.6.0.dist-info/top_level.txt
