Metadata-Version: 1.1
Name: model_mommy
Version: 1.6.0
Summary: Smart object creation facility for Django.
Home-page: http://github.com/vandersonmota/model_mommy
Author: vandersonmota
Author-email: vandersonmota@gmail.com
License: Apache 2.0
Keywords: django testing factory python
Platform: UNKNOWN
Classifier: Framework :: Django
Classifier: Intended Audience :: Developers
Classifier: License :: OSI Approved :: Apache Software License
Classifier: Operating System :: OS Independent
Classifier: Topic :: Software Development
Classifier: Programming Language :: Python :: 2
Classifier: Programming Language :: Python :: 2.7
Classifier: Programming Language :: Python :: 3
Classifier: Programming Language :: Python :: 3.5
Classifier: Programming Language :: Python :: 3.6
